LICENSE
MANIFEST.in
README.md
setup.py
helobomb/__init__.py
helobomb/bomber.py
helobomb.egg-info/PKG-INFO
helobomb.egg-info/SOURCES.txt
helobomb.egg-info/dependency_links.txt
helobomb.egg-info/entry_points.txt
helobomb.egg-info/requires.txt
helobomb.egg-info/top_level.txt
helobomb/utils/__init__.py
helobomb/utils/decorators.py
helobomb/utils/provider.py