Metadata-Version: 2.1
Name: helobomb
Version: 2.1.2
Summary: A free and open-source SMS,Call & Mail bombing application
Home-page: https://github.com/skvinderr/helobomb
Author: TheSpeedX
Author-email: skvinderr@gmail.com
License: GPL
Download-URL: https://github.com/skvinderr/helobomb/archive/refs/heads/pypi.zip
Keywords: android,spam,sms,mail,tbomb,call,bomb,termux,bomber,spammer
Platform: UNKNOWN
Classifier: Development Status :: 4 - Beta
Classifier: Intended Audience :: Developers
Classifier: Topic :: Software Development :: Libraries :: Python Modules
Classifier: License :: OSI Approved :: GNU General Public License v3 (GPLv3)
Classifier: Programming Language :: Python :: 3
Classifier: Operating System :: OS Independent
Classifier: Environment :: Console
Requires-Python: >=3.5
License-File: LICENSE
